disguise/__init__.py
disguise-0.0.1.dist-info/LICENSE
disguise-0.0.1.dist-info/METADATA
disguise-0.0.1.dist-info/WHEEL
disguise-0.0.1.dist-info/top_level.txt
disguise-0.0.1.dist-info/RECORD
