Metadata-Version: 2.1
Name: disguise
Version: 0.0.1
Summary: Initial stub
Home-page: https://github.com/gitlab/a10r/disguise
Author: Artem Likhvar
Author-email: me@a10r.com
License: UNKNOWN
Platform: UNKNOWN
Classifier: Programming Language :: Python :: 3
Classifier: License :: OSI Approved :: MIT License
Classifier: Operating System :: OS Independent
